deepanalyze/__init__.py
deepanalyze/_version.py
deepanalyze/agent_frontend_ops.py
deepanalyze/agent_llm_gateway.py
deepanalyze/agent_logging.py
deepanalyze/agent_model_store.py
deepanalyze/agent_openai_compat_client.py
deepanalyze/agent_orchestrator.py
deepanalyze/agent_prompt.py
deepanalyze/agent_prompt_builder.py
deepanalyze/agent_secret_store.py
deepanalyze/agent_session_store.py
deepanalyze/agent_settings.py
deepanalyze/agent_tag_parser.py
deepanalyze/agent_vllm_client.py
deepanalyze/agent_workspace_scanner.py
deepanalyze/handlers.py
deepanalyze/model_registry.py
deepanalyze/notebook_tools.py
deepanalyze/store_dir.py
deepanalyze/jupyter_server_config.d/deepanalyze.json
deepanalyze/models/index.json
deepanalyze/prompts/deepanalyze_8b.md
deepanalyze/prompts/deepanalyze_8b_ZH.md
deepanalyze/prompts/index.json
deepanalyze/prompts/universal_llm.md
deepanalyze/prompts/universal_llm_ZH.md
deepanalyze-0.2.0.data/data/etc/jupyter/jupyter_server_config.d/deepanalyze.json
deepanalyze-0.2.0.data/data/share/jupyter/labextensions/deepanalyze/build_log.json
deepanalyze-0.2.0.data/data/share/jupyter/labextensions/deepanalyze/package.json
deepanalyze-0.2.0.data/data/share/jupyter/labextensions/deepanalyze/static/7ac9d3809b43169488e0.png
deepanalyze-0.2.0.data/data/share/jupyter/labextensions/deepanalyze/static/lib_index_js.10b87fbb41f4b2f6fa68.js
deepanalyze-0.2.0.data/data/share/jupyter/labextensions/deepanalyze/static/lib_index_js.10b87fbb41f4b2f6fa68.js.map
deepanalyze-0.2.0.data/data/share/jupyter/labextensions/deepanalyze/static/remoteEntry.1b930b9a555ebeae4224.js
deepanalyze-0.2.0.data/data/share/jupyter/labextensions/deepanalyze/static/remoteEntry.1b930b9a555ebeae4224.js.map
deepanalyze-0.2.0.data/data/share/jupyter/labextensions/deepanalyze/static/style.js
deepanalyze-0.2.0.data/data/share/jupyter/labextensions/deepanalyze/static/style_index_js.72e88ce4e0d23ed148eb.js
deepanalyze-0.2.0.dist-info/METADATA
deepanalyze-0.2.0.dist-info/WHEEL
deepanalyze-0.2.0.dist-info/licenses/LICENSE
deepanalyze-0.2.0.dist-info/RECORD
