Metadata-Version: 2.4
Name: deepanalyze
Version: 0.2.0
Dynamic: Keywords
Summary: DeepAnalyze JupyterLab Extension
Project-URL: Homepage, https://github.com/github_username/deepanalyze
Project-URL: Bug Tracker, https://github.com/github_username/deepanalyze/issues
Project-URL: Repository, https://github.com/github_username/deepanalyze.git
Author-email: lyz <2655205682@qq.com>
License: BSD 3-Clause License
License-File: LICENSE
Classifier: Framework :: Jupyter
Classifier: Framework :: Jupyter :: JupyterLab
Classifier: Framework :: Jupyter :: JupyterLab :: 4
Classifier: Framework :: Jupyter :: JupyterLab :: Extensions
Classifier: Framework :: Jupyter :: JupyterLab :: Extensions :: Prebuilt
Classifier: License :: OSI Approved :: BSD License
Classifier: Programming Language :: Python
Classifier: Programming Language :: Python :: 3
Classifier: Programming Language :: Python :: 3.8
Classifier: Programming Language :: Python :: 3.9
Classifier: Programming Language :: Python :: 3.10
Classifier: Programming Language :: Python :: 3.11
Requires-Python: >=3.8
Requires-Dist: jupyter-server>=2.0.0
